sustainalytics/__init__.py
sustainalytics/api.py
sustainalytics/main.py
sustainalytics-0.3.4.dist-info/METADATA
sustainalytics-0.3.4.dist-info/WHEEL
sustainalytics-0.3.4.dist-info/RECORD
